[
  {"day": 1, "morning_humidity": 75, "afternoon_humidity": 60, "night_humidity": 80},
  {"day": 2, "morning_humidity": 70, "afternoon_humidity": 55, "night_humidity": 75},
  {"day": 3, "morning_humidity": 80, "afternoon_humidity": 65, "night_humidity": 85},
  {"day": 4, "morning_humidity": 72, "afternoon_humidity": 58, "night_humidity": 78},
  {"day": 5, "morning_humidity": 78, "afternoon_humidity": 62, "night_humidity": 82},
  {"day": 6, "morning_humidity": 82, "afternoon_humidity": 68, "night_humidity": 88},
  {"day": 7, "morning_humidity": 68, "afternoon_humidity": 52, "night_humidity": 72},
  {"day": 8, "morning_humidity": 85, "afternoon_humidity": 70, "night_humidity": 90},
  {"day": 9, "morning_humidity": 76, "afternoon_humidity": 63, "night_humidity": 83},
  {"day": 10, "morning_humidity": 73, "afternoon_humidity": 56, "night_humidity": 76},
  {"day": 11, "morning_humidity": 87, "afternoon_humidity": 72, "night_humidity": 92},
  {"day": 12, "morning_humidity": 71, "afternoon_humidity": 54, "night_humidity": 74},
  {"day": 13, "morning_humidity": 79, "afternoon_humidity": 60, "night_humidity": 81},
  {"day": 14, "morning_humidity": 83, "afternoon_humidity": 66, "night_humidity": 87},
  {"day": 15, "morning_humidity": 69, "afternoon_humidity": 50, "night_humidity": 71},
  {"day": 16, "morning_humidity": 88, "afternoon_humidity": 74, "night_humidity": 94},
  {"day": 17, "morning_humidity": 74, "afternoon_humidity": 57, "night_humidity": 77},
  {"day": 18, "morning_humidity": 81, "afternoon_humidity": 64, "night_humidity": 84},
  {"day": 19, "morning_humidity": 84, "afternoon_humidity": 69, "night_humidity": 89},
  {"day": 20, "morning_humidity": 67, "afternoon_humidity": 51, "night_humidity": 73},
  {"day": 21, "morning_humidity": 86, "afternoon_humidity": 71, "night_humidity": 91},
  {"day": 22, "morning_humidity": 75, "afternoon_humidity": 59, "night_humidity": 79},
  {"day": 23, "morning_humidity": 77, "afternoon_humidity": 61, "night_humidity": 80},
  {"day": 24, "morning_humidity": 70, "afternoon_humidity": 55, "night_humidity": 75},
  {"day": 25, "morning_humidity": 82, "afternoon_humidity": 67, "night_humidity": 86},
  {"day": 26, "morning_humidity": 72, "afternoon_humidity": 58, "night_humidity": 78},
  {"day": 27, "morning_humidity": 80, "afternoon_humidity": 64, "night_humidity": 83},
  {"day": 28, "morning_humidity": 85, "afternoon_humidity": 70, "night_humidity": 90},
  {"day": 29, "morning_humidity": 78, "afternoon_humidity": 62, "night_humidity": 82},
  {"day": 30, "morning_humidity": 74, "afternoon_humidity": 57, "night_humidity": 77},
{"day": 31, "morning_humidity": 79, "afternoon_humidity": 63, "night_humidity": 84},
  {"day": 32, "morning_humidity": 83, "afternoon_humidity": 68, "night_humidity": 88},
  {"day": 33, "morning_humidity": 69, "afternoon_humidity": 52, "night_humidity": 72},
  {"day": 34, "morning_humidity": 88, "afternoon_humidity": 74, "night_humidity": 94},
  {"day": 35, "morning_humidity": 74, "afternoon_humidity": 57, "night_humidity": 77},
  {"day": 36, "morning_humidity": 81, "afternoon_humidity": 64, "night_humidity": 84},
  {"day": 37, "morning_humidity": 84, "afternoon_humidity": 69, "night_humidity": 89},
  {"day": 38, "morning_humidity": 67, "afternoon_humidity": 51, "night_humidity": 73},
  {"day": 39, "morning_humidity": 86, "afternoon_humidity": 71, "night_humidity": 91},
  {"day": 40, "morning_humidity": 75, "afternoon_humidity": 59, "night_humidity": 79},
  {"day": 41, "morning_humidity": 77, "afternoon_humidity": 61, "night_humidity": 80},
  {"day": 42, "morning_humidity": 70, "afternoon_humidity": 55, "night_humidity": 75},
  {"day": 43, "morning_humidity": 82, "afternoon_humidity": 67, "night_humidity": 86},
  {"day": 44, "morning_humidity": 72, "afternoon_humidity": 58, "night_humidity": 78},
  {"day": 45, "morning_humidity": 80, "afternoon_humidity": 64, "night_humidity": 83},
  {"day": 46, "morning_humidity": 85, "afternoon_humidity": 70, "night_humidity": 90},
  {"day": 47, "morning_humidity": 78, "afternoon_humidity": 62, "night_humidity": 82},
  {"day": 48, "morning_humidity": 74, "afternoon_humidity": 57, "night_humidity": 77},
  {"day": 49, "morning_humidity": 81, "afternoon_humidity": 64, "night_humidity": 84},
  {"day": 50, "morning_humidity": 84, "afternoon_humidity": 69, "night_humidity": 89},
  {"day": 51, "morning_humidity": 67, "afternoon_humidity": 51, "night_humidity": 73},
  {"day": 52, "morning_humidity": 86, "afternoon_humidity": 71, "night_humidity": 91},
  {"day": 53, "morning_humidity": 75, "afternoon_humidity": 59, "night_humidity": 79},
  {"day": 54, "morning_humidity": 77, "afternoon_humidity": 61, "night_humidity": 80},
  {"day": 55, "morning_humidity": 70, "afternoon_humidity": 55, "night_humidity": 75},
  {"day": 56, "morning_humidity": 82, "afternoon_humidity": 67, "night_humidity": 86},
  {"day": 57, "morning_humidity": 72, "afternoon_humidity": 58, "night_humidity": 78},
  {"day": 58, "morning_humidity": 80, "afternoon_humidity": 64, "night_humidity": 83},
  {"day": 59, "morning_humidity": 85, "afternoon_humidity": 70, "night_humidity": 90},
  {"day": 60, "morning_humidity": 78, "afternoon_humidity": 62, "night_humidity": 82},
  {"day": 61, "morning_humidity": 74, "afternoon_humidity": 57, "night_humidity": 77},
  {"day": 62, "morning_humidity": 81, "afternoon_humidity": 64, "night_humidity": 84},
  {"day": 63, "morning_humidity": 84, "afternoon_humidity": 69, "night_humidity": 89},
  {"day": 64, "morning_humidity": 67, "afternoon_humidity": 51, "night_humidity": 73},
  {"day": 65, "morning_humidity": 86, "afternoon_humidity": 71, "night_humidity": 91},
  {"day": 66, "morning_humidity": 75, "afternoon_humidity": 59, "night_humidity": 79},
  {"day": 67, "morning_humidity": 77, "afternoon_humidity": 61, "night_humidity": 80},
  {"day": 68, "morning_humidity": 70, "afternoon_humidity": 55, "night_humidity": 75},
  {"day": 69, "morning_humidity": 82, "afternoon_humidity": 67, "night_humidity": 86},
  {"day": 70, "morning_humidity": 72, "afternoon_humidity": 58, "night_humidity": 78}

]
