[
    {
        "name": "Mount Everest",
        "location": "Nepal, China",
        "height_meters": 8848,
        "range": "Himalayas",
        "first_ascent_year": 1953,
        "prominence_meters": 8848
    },
    {
        "name": "K2",
        "location": "Pakistan, China",
        "height_meters": 8611,
        "range": "Karakoram",
        "first_ascent_year": 1954,
        "prominence_meters": 4017
    },
    {
        "name": "Mount Kilimanjaro",
        "location": "Tanzania",
        "height_meters": 5895,
        "range": "East Africa",
        "first_ascent_year": 1889,
        "prominence_meters": 5885
    },
    {
        "name": "Denali (Mount McKinley)",
        "location": "Alaska, USA",
        "height_meters": 6190,
        "range": "Alaska Range",
        "first_ascent_year": 1913,
        "prominence_meters": 6149
    },
    {
        "name": "Mont Blanc",
        "location": "France, Italy",
        "height_meters": 4808,
        "range": "Alps",
        "first_ascent_year": 1786,
        "prominence_meters": 4697
    }
]
[
    {
        "name": "Aconcagua",
        "location": "Argentina",
        "height_meters": 6962,
        "range": "Andes",
        "first_ascent_year": 1897,
        "prominence_meters": 6962
    },
    {
        "name": "Mount Elbrus",
        "location": "Russia",
        "height_meters": 5642,
        "range": "Caucasus",
        "first_ascent_year": 1874,
        "prominence_meters": 4741
    },
    {
        "name": "Matterhorn",
        "location": "Switzerland, Italy",
        "height_meters": 4478,
        "range": "Alps",
        "first_ascent_year": 1865,
        "prominence_meters": 1035
    },
    {
        "name": "Mount Fuji",
        "location": "Japan",
        "height_meters": 3776,
        "range": "Honshu",
        "first_ascent_year": "Unknown (early 8th century)",
        "prominence_meters": 3776
    },
    {
        "name": "Mount Olympus",
        "location": "Greece",
        "height_meters": 2918,
        "range": "Olympus Range",
        "first_ascent_year": "Ancient times",
        "prominence_meters": 2353
    },
    {
        "name": "Mount Rainier",
        "location": "Washington, USA",
        "height_meters": 4392,
        "range": "Cascade Range",
        "first_ascent_year": 1870,
        "prominence_meters": 4026
    },
    {
        "name": "Ben Nevis",
        "location": "Scotland",
        "height_meters": 1345,
        "range": "Grampian Mountains",
        "first_ascent_year": 1771,
        "prominence_meters": 1345
    },
    {
        "name": "Mount Cook (Aoraki)",
        "location": "New Zealand",
        "height_meters": 3724,
        "range": "Southern Alps",
        "first_ascent_year": 1894,
        "prominence_meters": 3724
    },
    {
        "name": "Mount McKinley",
        "location": "Alaska, USA",
        "height_meters": 6190,
        "range": "Alaska Range",
        "first_ascent_year": 1913,
        "prominence_meters": 6149
    },
    {
        "name": "Kilimanjaro",
        "location": "Tanzania",
        "height_meters": 5895,
        "range": "East Africa",
        "first_ascent_year": 1889,
        "prominence_meters": 5885
    }
]
[
    {
        "name": "Table Mountain",
        "location": "South Africa",
        "height_meters": 1086,
        "range": "Cape Peninsula",
        "first_ascent_year": "Not applicable",
        "prominence_meters": 1086
    },
    {
        "name": "Mount Ararat",
        "location": "Turkey",
        "height_meters": 5137,
        "range": "Ararat Massif",
        "first_ascent_year": "Not documented",
        "prominence_meters": 3611
    },
    {
        "name": "Mount Vesuvius",
        "location": "Italy",
        "height_meters": 1281,
        "range": "Apennines",
        "first_ascent_year": "Not applicable",
        "prominence_meters": 1281
    },
    {
        "name": "Mauna Kea",
        "location": "Hawaii, USA",
        "height_meters": 4207,
        "range": "Hawaiian Islands",
        "first_ascent_year": "Cultural significance",
        "prominence_meters": 4207
    },
    {
        "name": "Mount Etna",
        "location": "Italy",
        "height_meters": 3329,
        "range": "Sicily",
        "first_ascent_year": "Not applicable",
        "prominence_meters": 3329
    },
    {
        "name": "Mount Kosciuszko",
        "location": "Australia",
        "height_meters": 2228,
        "range": "Great Dividing Range",
        "first_ascent_year": 1840,
        "prominence_meters": 2228
    },
    {
        "name": "Puncak Jaya (Carstensz Pyramid)",
        "location": "Indonesia",
        "height_meters": 4884,
        "range": "Sudirman Range",
        "first_ascent_year": 1962,
        "prominence_meters": 4884
    },
    {
        "name": "Mount Blanc",
        "location": "France, Italy",
        "height_meters": 4808,
        "range": "Alps",
        "first_ascent_year": 1786,
        "prominence_meters": 4697
    },
    {
        "name": "Mount Elgon",
        "location": "Uganda, Kenya",
        "height_meters": 4321,
        "range": "Eastern Rift Mountains",
        "first_ascent_year": "Not documented",
        "prominence_meters": 2458
    },
    {
        "name": "Mount Olympus",
        "location": "Greece",
        "height_meters": 2918,
        "range": "Olympus Range",
        "first_ascent_year": "Ancient times",
        "prominence_meters": 2353
    }
]
[
    {
        "name": "Mount Cook (Aoraki)",
        "location": "New Zealand",
        "height_meters": 3724,
        "range": "Southern Alps",
        "first_ascent_year": 1894,
        "prominence_meters": 3724
    },
    {
        "name": "Mount Whitney",
        "location": "California, USA",
        "height_meters": 4421,
        "range": "Sierra Nevada",
        "first_ascent_year": 1873,
        "prominence_meters": 3072
    },
    {
        "name": "Mount Olympus",
        "location": "Washington, USA",
        "height_meters": 2429,
        "range": "Olympic Mountains",
        "first_ascent_year": 1907,
        "prominence_meters": 2389
    },
    {
        "name": "Mount Shasta",
        "location": "California, USA",
        "height_meters": 4322,
        "range": "Cascade Range",
        "first_ascent_year": 1854,
        "prominence_meters": 2975
    },
    {
        "name": "Mount Hood",
        "location": "Oregon, USA",
        "height_meters": 3429,
        "range": "Cascade Range",
        "first_ascent_year": 1857,
        "prominence_meters": 2349
    },
    {
        "name": "Mount Kenya",
        "location": "Kenya",
        "height_meters": 5199,
        "range": "Kenya Rift Valley",
        "first_ascent_year": 1899,
        "prominence_meters": 3825
    },
    {
        "name": "Mount Eiger",
        "location": "Switzerland",
        "height_meters": 3970,
        "range": "Bernese Alps",
        "first_ascent_year": 1858,
        "prominence_meters": 1560
    },
    {
        "name": "Mount Olympus",
        "location": "Cyprus",
        "height_meters": 1952,
        "range": "Troodos Mountains",
        "first_ascent_year": "Not documented",
        "prominence_meters": 1952
    },
    {
        "name": "Mount Aragats",
        "location": "Armenia",
        "height_meters": 4090,
        "range": "Aragats Range",
        "first_ascent_year": "Not documented",
        "prominence_meters": 2155
    },
    {
        "name": "Mount Cook",
        "location": "Antarctica",
        "height_meters": 4093,
        "range": "Transantarctic Mountains",
        "first_ascent_year": 1967,
        "prominence_meters": 4093
    }
]
[
    {
        "name": "Mount Roraima",
        "location": "Venezuela, Guyana, Brazil",
        "height_meters": 2810,
        "range": "Guiana Highlands",
        "first_ascent_year": 1884,
        "prominence_meters": 2338
    },
    {
        "name": "Mount Bromo",
        "location": "Indonesia",
        "height_meters": 2329,
        "range": "Tengger Massif",
        "first_ascent_year": "Not applicable",
        "prominence_meters": 600
    },
    {
        "name": "Mount Kinabalu",
        "location": "Malaysia",
        "height_meters": 4095,
        "range": "Crocker Range",
        "first_ascent_year": 1851,
        "prominence_meters": 4095
    },
    {
        "name": "Mount Damavand",
        "location": "Iran",
        "height_meters": 5610,
        "range": "Alborz",
        "first_ascent_year": "Not documented",
        "prominence_meters": 4667
    },
    {
        "name": "Mount Thor",
        "location": "Canada",
        "height_meters": 1675,
        "range": "Baffin Mountains",
        "first_ascent_year": 1965,
        "prominence_meters": 1259
    },
    {
        "name": "Mount Olympus",
        "location": "Mars",
        "height_meters": 21148,
        "range": "Mars Range",
        "first_ascent_year": "Not applicable",
        "prominence_meters": 21148
    },
    {
        "name": "Mount Erebus",
        "location": "Antarctica",
        "height_meters": 3794,
        "range": "Transantarctic Mountains",
        "first_ascent_year": 1908,
        "prominence_meters": 3794
    },
    {
        "name": "Mount Olympus",
        "location": "Washington, USA",
        "height_meters": 2429,
        "range": "Olympic Mountains",
        "first_ascent_year": 1907,
        "prominence_meters": 2389
    },
    {
        "name": "Mount Ararat",
        "location": "Turkey",
        "height_meters": 5137,
        "range": "Ararat Massif",
        "first_ascent_year": "Not documented",
        "prominence_meters": 3611
    },
    {
        "name": "Mount Asgard",
        "location": "Canada",
        "height_meters": 2015,
        "range": "Baffin Island",
        "first_ascent_year": 1953,
        "prominence_meters": 2015
    }
]
[
    {
        "name": "Mount Olympus",
        "location": "Greece",
        "height_meters": 2918,
        "range": "Olympus Range",
        "first_ascent_year": "Ancient times",
        "prominence_meters": 2353
    },
    {
        "name": "Mount Cook (Aoraki)",
        "location": "New Zealand",
        "height_meters": 3724,
        "range": "Southern Alps",
        "first_ascent_year": 1894,
        "prominence_meters": 3724
    },
    {
        "name": "Mount Robson",
        "location": "Canada",
        "height_meters": 3954,
        "range": "Canadian Rockies",
        "first_ascent_year": 1913,
        "prominence_meters": 2812
    },
    {
        "name": "Mount Fuji",
        "location": "Japan",
        "height_meters": 3776,
        "range": "Honshu",
        "first_ascent_year": "Unknown (early 8th century)",
        "prominence_meters": 3776
    },
    {
        "name": "Mount Kenya",
        "location": "Kenya",
        "height_meters": 5199,
        "range": "Kenya Rift Valley",
        "first_ascent_year": 1899,
        "prominence_meters": 3825
    },
    {
        "name": "Mount St. Helens",
        "location": "Washington, USA",
        "height_meters": 2549,
        "range": "Cascade Range",
        "first_ascent_year": 1853,
        "prominence_meters": 1398
    },
    {
        "name": "Mount Vesuvius",
        "location": "Italy",
        "height_meters": 1281,
        "range": "Apennines",
        "first_ascent_year": "Not applicable",
        "prominence_meters": 1281
    },
    {
        "name": "Mount Kilimanjaro",
        "location": "Tanzania",
        "height_meters": 5895,
        "range": "East Africa",
        "first_ascent_year": 1889,
        "prominence_meters": 5885
    },
    {
        "name": "Mount Olympus",
        "location": "Cyprus",
        "height_meters": 1952,
        "range": "Troodos Mountains",
        "first_ascent_year": "Not documented",
        "prominence_meters": 1952
    },
    {
        "name": "Mount McKinley",
        "location": "Alaska, USA",
        "height_meters": 6190,
        "range": "Alaska Range",
        "first_ascent_year": 1913,
        "prominence_meters": 6149
    }
]
[
    {
        "name": "Mount Etna",
        "location": "Italy",
        "height_meters": 3329,
        "range": "Sicily",
        "first_ascent_year": "Not applicable",
        "prominence_meters": 3329
    },
    {
        "name": "Mount Kilimanjaro",
        "location": "Tanzania",
        "height_meters": 5895,
        "range": "East Africa",
        "first_ascent_year": 1889,
        "prominence_meters": 5885
    },
    {
        "name": "Mount Kinabalu",
        "location": "Malaysia",
        "height_meters": 4095,
        "range": "Crocker Range",
        "first_ascent_year": 1851,
        "prominence_meters": 4095
    },
    {
        "name": "Mount Whitney",
        "location": "California, USA",
        "height_meters": 4421,
        "range": "Sierra Nevada",
        "first_ascent_year": 1873,
        "prominence_meters": 3072
    },
    {
        "name": "Mount Olympus",
        "location": "Washington, USA",
        "height_meters": 2429,
        "range": "Olympic Mountains",
        "first_ascent_year": 1907,
        "prominence_meters": 2389
    },
    {
        "name": "Mount Elbrus",
        "location": "Russia",
        "height_meters": 5642,
        "range": "Caucasus",
        "first_ascent_year": 1874,
        "prominence_meters": 4741
    },
    {
        "name": "Mount Logan",
        "location": "Canada",
        "height_meters": 5959,
        "range": "Saint Elias Mountains",
        "first_ascent_year": 1925,
        "prominence_meters": 5247
    },
    {
        "name": "Mount Shasta",
        "location": "California, USA",
        "height_meters": 4322,
        "range": "Cascade Range",
        "first_ascent_year": 1854,
        "prominence_meters": 2975
    },
    {
        "name": "Mount Baker",
        "location": "Washington, USA",
        "height_meters": 3286,
        "range": "Cascade Range",
        "first_ascent_year": 1868,
        "prominence_meters": 2714
    },
    {
        "name": "Mount Cook (Aoraki)",
        "location": "New Zealand",
        "height_meters": 3724,
        "range": "Southern Alps",
        "first_ascent_year": 1894,
        "prominence_meters": 3724
    }
]
